{
  "manifestVersion": "3.2",
  "proxies": [
    {
      "address": "0x936E6aEF9A5907Dc0de39d2Ecb0D25f0B5929F15",
      "txHash": "0xdf10d21ffbb80c7886d9cf112fca35e8c04c08824eae738e3178403422a930ec",
      "remoteDeploymentId": "2f11a5cd-7dc7-41c9-9fc9-9c8d54403f5c",
      "kind": "uups"
    },
    {
      "address": "0xbB700A7d2fECc1cb30d1834E5d3965B31FAcc67F",
      "txHash": "0x2c3fc0373a61ec31326490df3ff89bed4a8be4ffca84b50be9da9f71e7ccd0d5",
      "remoteDeploymentId": "501f9334-2bc1-41f4-ad1e-0d051008c8d8",
      "kind": "uups"
    },
    {
      "address": "0xab7fe96ed01dd9782C5c4544aB93304CF4FCD10A",
      "txHash": "0xcf597fbc5242997ecf1ef68a28d3d713b901bb0b278d5b4c005d2e440df50c32",
      "remoteDeploymentId": "da933788-42f2-426f-b08b-14387c556140",
      "kind": "uups"
    }
  ],
  "impls": {
    "a285de434a3dad0a164d9eefa43ab0fe119756b319bfc556fb75a5438a67061a": {
      "address": "0x465C6Bbf1Fc15216604F96632aA227251e4Dc879",
      "txHash": "0x79f14c2a2d1841669f806df84d69652810ee18b20af5b84d899c12113832eefe",
      "remoteDeploymentId": "36b372e5-3caa-49b5-9be7-1899800a359e",
      "layout": {
        "solcVersion": "0.8.20",
        "storage": [
          {
            "label": "idCounter",
            "offset": 0,
            "slot": "0",
            "type": "t_uint256",
            "contract": "Crowdfunding",
            "src": "contracts/Crowdfunding.sol:39"
          },
          {
            "label": "supportedTokens",
            "offset": 0,
            "slot": "1",
            "type": "t_mapping(t_address,t_bool)",
            "contract": "Crowdfunding",
            "src": "contracts/Crowdfunding.sol:42"
          },
          {
            "label": "projects",
            "offset": 0,
            "slot": "2",
            "type": "t_mapping(t_uint256,t_struct(Project)6350_storage)",
            "contract": "Crowdfunding",
            "src": "contracts/Crowdfunding.sol:44"
          },
          {
            "label": "projectsThresholds",
            "offset": 0,
            "slot": "3",
            "type": "t_mapping(t_uint256,t_mapping(t_uint256,t_struct(Threshold)6288_storage))",
            "contract": "Crowdfunding",
            "src": "contracts/Crowdfunding.sol:47"
          },
          {
            "label": "userDonations",
            "offset": 0,
            "slot": "4",
            "type": "t_mapping(t_address,t_mapping(t_uint256,t_uint256))",
            "contract": "Crowdfunding",
            "src": "contracts/Crowdfunding.sol:50"
          },
          {
            "label": "thresholdVoteFromAddress",
            "offset": 0,
            "slot": "5",
            "type": "t_mapping(t_address,t_mapping(t_uint256,t_mapping(t_uint256,t_bool)))",
            "contract": "Crowdfunding",
            "src": "contracts/Crowdfunding.sol:52"
          },
          {
            "label": "voterArrayForThreshold",
            "offset": 0,
            "slot": "6",
            "type": "t_mapping(t_uint256,t_mapping(t_uint256,t_array(t_address)dyn_storage))",
            "contract": "Crowdfunding",
            "src": "contracts/Crowdfunding.sol:55"
          },
          {
            "label": "availableFees",
            "offset": 0,
            "slot": "7",
            "type": "t_mapping(t_address,t_uint256)",
            "contract": "Crowdfunding",
            "src": "contracts/Crowdfunding.sol:59"
          }
        ],
        "types": {
          "t_address": {
            "label": "address",
            "numberOfBytes": "20"
          },
          "t_bool": {
            "label": "bool",
            "numberOfBytes": "1"
          },
          "t_bytes32": {
            "label": "bytes32",
            "numberOfBytes": "32"
          },
          "t_mapping(t_address,t_bool)": {
            "label": "mapping(address => bool)",
            "numberOfBytes": "32"
          },
          "t_mapping(t_bytes32,t_struct(RoleData)25_storage)": {
            "label": "mapping(bytes32 => struct AccessControlUpgradeable.RoleData)",
            "numberOfBytes": "32"
          },
          "t_struct(AccessControlStorage)34_storage": {
            "label": "struct AccessControlUpgradeable.AccessControlStorage",
            "members": [
              {
                "label": "_roles",
                "type": "t_mapping(t_bytes32,t_struct(RoleData)25_storage)",
                "offset": 0,
                "slot": "0"
              }
            ],
            "numberOfBytes": "32"
          },
          "t_struct(InitializableStorage)93_storage": {
            "label": "struct Initializable.InitializableStorage",
            "members": [
              {
                "label": "_initialized",
                "type": "t_uint64",
                "offset": 0,
                "slot": "0"
              },
              {
                "label": "_initializing",
                "type": "t_bool",
                "offset": 8,
                "slot": "0"
              }
            ],
            "numberOfBytes": "32"
          },
          "t_struct(PausableStorage)217_storage": {
            "label": "struct PausableUpgradeable.PausableStorage",
            "members": [
              {
                "label": "_paused",
                "type": "t_bool",
                "offset": 0,
                "slot": "0"
              }
            ],
            "numberOfBytes": "32"
          },
          "t_struct(RoleData)25_storage": {
            "label": "struct AccessControlUpgradeable.RoleData",
            "members": [
              {
                "label": "hasRole",
                "type": "t_mapping(t_address,t_bool)",
                "offset": 0,
                "slot": "0"
              },
              {
                "label": "adminRole",
                "type": "t_bytes32",
                "offset": 0,
                "slot": "1"
              }
            ],
            "numberOfBytes": "64"
          },
          "t_uint64": {
            "label": "uint64",
            "numberOfBytes": "8"
          },
          "t_array(t_address)dyn_storage": {
            "label": "address[]",
            "numberOfBytes": "32"
          },
          "t_mapping(t_address,t_mapping(t_uint256,t_mapping(t_uint256,t_bool)))": {
            "label": "mapping(address => mapping(uint256 => mapping(uint256 => bool)))",
            "numberOfBytes": "32"
          },
          "t_mapping(t_address,t_mapping(t_uint256,t_uint256))": {
            "label": "mapping(address => mapping(uint256 => uint256))",
            "numberOfBytes": "32"
          },
          "t_mapping(t_address,t_uint256)": {
            "label": "mapping(address => uint256)",
            "numberOfBytes": "32"
          },
          "t_mapping(t_uint256,t_array(t_address)dyn_storage)": {
            "label": "mapping(uint256 => address[])",
            "numberOfBytes": "32"
          },
          "t_mapping(t_uint256,t_bool)": {
            "label": "mapping(uint256 => bool)",
            "numberOfBytes": "32"
          },
          "t_mapping(t_uint256,t_mapping(t_uint256,t_array(t_address)dyn_storage))": {
            "label": "mapping(uint256 => mapping(uint256 => address[]))",
            "numberOfBytes": "32"
          },
          "t_mapping(t_uint256,t_mapping(t_uint256,t_bool))": {
            "label": "mapping(uint256 => mapping(uint256 => bool))",
            "numberOfBytes": "32"
          },
          "t_mapping(t_uint256,t_mapping(t_uint256,t_struct(Threshold)6288_storage))": {
            "label": "mapping(uint256 => mapping(uint256 => struct ICrowdfunding.Threshold))",
            "numberOfBytes": "32"
          },
          "t_mapping(t_uint256,t_struct(Project)6350_storage)": {
            "label": "mapping(uint256 => struct ICrowdfunding.Project)",
            "numberOfBytes": "32"
          },
          "t_mapping(t_uint256,t_struct(Threshold)6288_storage)": {
            "label": "mapping(uint256 => struct ICrowdfunding.Threshold)",
            "numberOfBytes": "32"
          },
          "t_mapping(t_uint256,t_uint256)": {
            "label": "mapping(uint256 => uint256)",
            "numberOfBytes": "32"
          },
          "t_string_storage": {
            "label": "string",
            "numberOfBytes": "32"
          },
          "t_struct(Project)6350_storage": {
            "label": "struct ICrowdfunding.Project",
            "members": [
              {
                "label": "isActive",
                "type": "t_bool",
                "offset": 0,
                "slot": "0"
              },
              {
                "label": "owner",
                "type": "t_address",
                "offset": 1,
                "slot": "0"
              },
              {
                "label": "exchangeTokenAddress",
                "type": "t_address",
                "offset": 0,
                "slot": "1"
              },
              {
                "label": "name",
                "type": "t_string_storage",
                "offset": 0,
                "slot": "2"
              },
              {
                "label": "assoName",
                "type": "t_string_storage",
                "offset": 0,
                "slot": "3"
              },
              {
                "label": "description",
                "type": "t_string_storage",
                "offset": 0,
                "slot": "4"
              },
              {
                "label": "requiredAmount",
                "type": "t_uint256",
                "offset": 0,
                "slot": "5"
              },
              {
                "label": "currentAmount",
                "type": "t_uint256",
                "offset": 0,
                "slot": "6"
              },
              {
                "label": "availableToWithdraw",
                "type": "t_uint256",
                "offset": 0,
                "slot": "7"
              },
              {
                "label": "amountWithdrawn",
                "type": "t_uint256",
                "offset": 0,
                "slot": "8"
              },
              {
                "label": "currentThreshold",
                "type": "t_uint256",
                "offset": 0,
                "slot": "9"
              },
              {
                "label": "nbOfThresholds",
                "type": "t_uint256",
                "offset": 0,
                "slot": "10"
              },
              {
                "label": "requiredVotePercentage",
                "type": "t_uint256",
                "offset": 0,
                "slot": "11"
              },
              {
                "label": "voteCooldown",
                "type": "t_uint256",
                "offset": 0,
                "slot": "12"
              },
              {
                "label": "currentVoteCooldown",
                "type": "t_uint256",
                "offset": 0,
                "slot": "13"
              },
              {
                "label": "donationFee",
                "type": "t_uint16",
                "offset": 0,
                "slot": "14"
              }
            ],
            "numberOfBytes": "480"
          },
          "t_struct(Threshold)6288_storage": {
            "label": "struct ICrowdfunding.Threshold",
            "members": [
              {
                "label": "budget",
                "type": "t_uint256",
                "offset": 0,
                "slot": "0"
              },
              {
                "label": "voteSession",
                "type": "t_struct(VoteSession)6296_storage",
                "offset": 0,
                "slot": "1"
              }
            ],
            "numberOfBytes": "128"
          },
          "t_struct(VoteSession)6296_storage": {
            "label": "struct ICrowdfunding.VoteSession",
            "members": [
              {
                "label": "isVotingInSession",
                "type": "t_bool",
                "offset": 0,
                "slot": "0"
              },
              {
                "label": "positiveVotes",
                "type": "t_uint256",
                "offset": 0,
                "slot": "1"
              },
              {
                "label": "negativeVotes",
                "type": "t_uint256",
                "offset": 0,
                "slot": "2"
              }
            ],
            "numberOfBytes": "96"
          },
          "t_uint16": {
            "label": "uint16",
            "numberOfBytes": "2"
          },
          "t_uint256": {
            "label": "uint256",
            "numberOfBytes": "32"
          }
        },
        "namespaces": {
          "erc7201:openzeppelin.storage.Pausable": [
            {
              "contract": "PausableUpgradeable",
              "label": "_paused",
              "type": "t_bool",
              "src": "@openzeppelin/contracts-upgradeable/utils/PausableUpgradeable.sol:21",
              "offset": 0,
              "slot": "0"
            }
          ],
          "erc7201:openzeppelin.storage.AccessControl": [
            {
              "contract": "AccessControlUpgradeable",
              "label": "_roles",
              "type": "t_mapping(t_bytes32,t_struct(RoleData)25_storage)",
              "src": "@openzeppelin/contracts-upgradeable/access/AccessControlUpgradeable.sol:61",
              "offset": 0,
              "slot": "0"
            }
          ],
          "erc7201:openzeppelin.storage.Initializable": [
            {
              "contract": "Initializable",
              "label": "_initialized",
              "type": "t_uint64",
              "src": "@openzeppelin/contracts-upgradeable/proxy/utils/Initializable.sol:69",
              "offset": 0,
              "slot": "0"
            },
            {
              "contract": "Initializable",
              "label": "_initializing",
              "type": "t_bool",
              "src": "@openzeppelin/contracts-upgradeable/proxy/utils/Initializable.sol:73",
              "offset": 8,
              "slot": "0"
            }
          ]
        }
      }
    },
    "6db17a0e883b2796e9b29effc00826efb80f16d31721d94ffaae41f0555a1cf2": {
      "address": "0xc00A0018C4Cb99b901DD54A2191Dfec5C64EFa79",
      "txHash": "0xf7a715d8b84273f9ed3f1a0bc64efb2e9dbe2f9237d8186ff06209b4921a9f4b",
      "remoteDeploymentId": "e93e364b-2289-4f14-9815-b00cafe4c2b8",
      "layout": {
        "solcVersion": "0.8.20",
        "storage": [
          {
            "label": "idCounter",
            "offset": 0,
            "slot": "0",
            "type": "t_uint256",
            "contract": "CrowdfundingV2",
            "src": "contracts/CrowdfundingV2.sol:39"
          },
          {
            "label": "supportedTokens",
            "offset": 0,
            "slot": "1",
            "type": "t_mapping(t_address,t_bool)",
            "contract": "CrowdfundingV2",
            "src": "contracts/CrowdfundingV2.sol:42"
          },
          {
            "label": "projects",
            "offset": 0,
            "slot": "2",
            "type": "t_mapping(t_uint256,t_struct(Project)6350_storage)",
            "contract": "CrowdfundingV2",
            "src": "contracts/CrowdfundingV2.sol:44"
          },
          {
            "label": "projectsThresholds",
            "offset": 0,
            "slot": "3",
            "type": "t_mapping(t_uint256,t_mapping(t_uint256,t_struct(Threshold)6288_storage))",
            "contract": "CrowdfundingV2",
            "src": "contracts/CrowdfundingV2.sol:47"
          },
          {
            "label": "userDonations",
            "offset": 0,
            "slot": "4",
            "type": "t_mapping(t_address,t_mapping(t_uint256,t_uint256))",
            "contract": "CrowdfundingV2",
            "src": "contracts/CrowdfundingV2.sol:50"
          },
          {
            "label": "thresholdVoteFromAddress",
            "offset": 0,
            "slot": "5",
            "type": "t_mapping(t_address,t_mapping(t_uint256,t_mapping(t_uint256,t_bool)))",
            "contract": "CrowdfundingV2",
            "src": "contracts/CrowdfundingV2.sol:52"
          },
          {
            "label": "voterArrayForThreshold",
            "offset": 0,
            "slot": "6",
            "type": "t_mapping(t_uint256,t_mapping(t_uint256,t_array(t_address)dyn_storage))",
            "contract": "CrowdfundingV2",
            "src": "contracts/CrowdfundingV2.sol:55"
          },
          {
            "label": "availableFees",
            "offset": 0,
            "slot": "7",
            "type": "t_mapping(t_address,t_uint256)",
            "contract": "CrowdfundingV2",
            "src": "contracts/CrowdfundingV2.sol:59"
          },
          {
            "label": "myNewvariable",
            "offset": 0,
            "slot": "8",
            "type": "t_uint256",
            "contract": "CrowdfundingV2",
            "src": "contracts/CrowdfundingV2.sol:757"
          }
        ],
        "types": {
          "t_address": {
            "label": "address",
            "numberOfBytes": "20"
          },
          "t_bool": {
            "label": "bool",
            "numberOfBytes": "1"
          },
          "t_bytes32": {
            "label": "bytes32",
            "numberOfBytes": "32"
          },
          "t_mapping(t_address,t_bool)": {
            "label": "mapping(address => bool)",
            "numberOfBytes": "32"
          },
          "t_mapping(t_bytes32,t_struct(RoleData)25_storage)": {
            "label": "mapping(bytes32 => struct AccessControlUpgradeable.RoleData)",
            "numberOfBytes": "32"
          },
          "t_struct(AccessControlStorage)34_storage": {
            "label": "struct AccessControlUpgradeable.AccessControlStorage",
            "members": [
              {
                "label": "_roles",
                "type": "t_mapping(t_bytes32,t_struct(RoleData)25_storage)",
                "offset": 0,
                "slot": "0"
              }
            ],
            "numberOfBytes": "32"
          },
          "t_struct(InitializableStorage)93_storage": {
            "label": "struct Initializable.InitializableStorage",
            "members": [
              {
                "label": "_initialized",
                "type": "t_uint64",
                "offset": 0,
                "slot": "0"
              },
              {
                "label": "_initializing",
                "type": "t_bool",
                "offset": 8,
                "slot": "0"
              }
            ],
            "numberOfBytes": "32"
          },
          "t_struct(PausableStorage)217_storage": {
            "label": "struct PausableUpgradeable.PausableStorage",
            "members": [
              {
                "label": "_paused",
                "type": "t_bool",
                "offset": 0,
                "slot": "0"
              }
            ],
            "numberOfBytes": "32"
          },
          "t_struct(RoleData)25_storage": {
            "label": "struct AccessControlUpgradeable.RoleData",
            "members": [
              {
                "label": "hasRole",
                "type": "t_mapping(t_address,t_bool)",
                "offset": 0,
                "slot": "0"
              },
              {
                "label": "adminRole",
                "type": "t_bytes32",
                "offset": 0,
                "slot": "1"
              }
            ],
            "numberOfBytes": "64"
          },
          "t_uint64": {
            "label": "uint64",
            "numberOfBytes": "8"
          },
          "t_array(t_address)dyn_storage": {
            "label": "address[]",
            "numberOfBytes": "32"
          },
          "t_mapping(t_address,t_mapping(t_uint256,t_mapping(t_uint256,t_bool)))": {
            "label": "mapping(address => mapping(uint256 => mapping(uint256 => bool)))",
            "numberOfBytes": "32"
          },
          "t_mapping(t_address,t_mapping(t_uint256,t_uint256))": {
            "label": "mapping(address => mapping(uint256 => uint256))",
            "numberOfBytes": "32"
          },
          "t_mapping(t_address,t_uint256)": {
            "label": "mapping(address => uint256)",
            "numberOfBytes": "32"
          },
          "t_mapping(t_uint256,t_array(t_address)dyn_storage)": {
            "label": "mapping(uint256 => address[])",
            "numberOfBytes": "32"
          },
          "t_mapping(t_uint256,t_bool)": {
            "label": "mapping(uint256 => bool)",
            "numberOfBytes": "32"
          },
          "t_mapping(t_uint256,t_mapping(t_uint256,t_array(t_address)dyn_storage))": {
            "label": "mapping(uint256 => mapping(uint256 => address[]))",
            "numberOfBytes": "32"
          },
          "t_mapping(t_uint256,t_mapping(t_uint256,t_bool))": {
            "label": "mapping(uint256 => mapping(uint256 => bool))",
            "numberOfBytes": "32"
          },
          "t_mapping(t_uint256,t_mapping(t_uint256,t_struct(Threshold)6288_storage))": {
            "label": "mapping(uint256 => mapping(uint256 => struct ICrowdfunding.Threshold))",
            "numberOfBytes": "32"
          },
          "t_mapping(t_uint256,t_struct(Project)6350_storage)": {
            "label": "mapping(uint256 => struct ICrowdfunding.Project)",
            "numberOfBytes": "32"
          },
          "t_mapping(t_uint256,t_struct(Threshold)6288_storage)": {
            "label": "mapping(uint256 => struct ICrowdfunding.Threshold)",
            "numberOfBytes": "32"
          },
          "t_mapping(t_uint256,t_uint256)": {
            "label": "mapping(uint256 => uint256)",
            "numberOfBytes": "32"
          },
          "t_string_storage": {
            "label": "string",
            "numberOfBytes": "32"
          },
          "t_struct(Project)6350_storage": {
            "label": "struct ICrowdfunding.Project",
            "members": [
              {
                "label": "isActive",
                "type": "t_bool",
                "offset": 0,
                "slot": "0"
              },
              {
                "label": "owner",
                "type": "t_address",
                "offset": 1,
                "slot": "0"
              },
              {
                "label": "exchangeTokenAddress",
                "type": "t_address",
                "offset": 0,
                "slot": "1"
              },
              {
                "label": "name",
                "type": "t_string_storage",
                "offset": 0,
                "slot": "2"
              },
              {
                "label": "assoName",
                "type": "t_string_storage",
                "offset": 0,
                "slot": "3"
              },
              {
                "label": "description",
                "type": "t_string_storage",
                "offset": 0,
                "slot": "4"
              },
              {
                "label": "requiredAmount",
                "type": "t_uint256",
                "offset": 0,
                "slot": "5"
              },
              {
                "label": "currentAmount",
                "type": "t_uint256",
                "offset": 0,
                "slot": "6"
              },
              {
                "label": "availableToWithdraw",
                "type": "t_uint256",
                "offset": 0,
                "slot": "7"
              },
              {
                "label": "amountWithdrawn",
                "type": "t_uint256",
                "offset": 0,
                "slot": "8"
              },
              {
                "label": "currentThreshold",
                "type": "t_uint256",
                "offset": 0,
                "slot": "9"
              },
              {
                "label": "nbOfThresholds",
                "type": "t_uint256",
                "offset": 0,
                "slot": "10"
              },
              {
                "label": "requiredVotePercentage",
                "type": "t_uint256",
                "offset": 0,
                "slot": "11"
              },
              {
                "label": "voteCooldown",
                "type": "t_uint256",
                "offset": 0,
                "slot": "12"
              },
              {
                "label": "currentVoteCooldown",
                "type": "t_uint256",
                "offset": 0,
                "slot": "13"
              },
              {
                "label": "donationFee",
                "type": "t_uint16",
                "offset": 0,
                "slot": "14"
              }
            ],
            "numberOfBytes": "480"
          },
          "t_struct(Threshold)6288_storage": {
            "label": "struct ICrowdfunding.Threshold",
            "members": [
              {
                "label": "budget",
                "type": "t_uint256",
                "offset": 0,
                "slot": "0"
              },
              {
                "label": "voteSession",
                "type": "t_struct(VoteSession)6296_storage",
                "offset": 0,
                "slot": "1"
              }
            ],
            "numberOfBytes": "128"
          },
          "t_struct(VoteSession)6296_storage": {
            "label": "struct ICrowdfunding.VoteSession",
            "members": [
              {
                "label": "isVotingInSession",
                "type": "t_bool",
                "offset": 0,
                "slot": "0"
              },
              {
                "label": "positiveVotes",
                "type": "t_uint256",
                "offset": 0,
                "slot": "1"
              },
              {
                "label": "negativeVotes",
                "type": "t_uint256",
                "offset": 0,
                "slot": "2"
              }
            ],
            "numberOfBytes": "96"
          },
          "t_uint16": {
            "label": "uint16",
            "numberOfBytes": "2"
          },
          "t_uint256": {
            "label": "uint256",
            "numberOfBytes": "32"
          }
        },
        "namespaces": {
          "erc7201:openzeppelin.storage.Pausable": [
            {
              "contract": "PausableUpgradeable",
              "label": "_paused",
              "type": "t_bool",
              "src": "@openzeppelin/contracts-upgradeable/utils/PausableUpgradeable.sol:21",
              "offset": 0,
              "slot": "0"
            }
          ],
          "erc7201:openzeppelin.storage.AccessControl": [
            {
              "contract": "AccessControlUpgradeable",
              "label": "_roles",
              "type": "t_mapping(t_bytes32,t_struct(RoleData)25_storage)",
              "src": "@openzeppelin/contracts-upgradeable/access/AccessControlUpgradeable.sol:61",
              "offset": 0,
              "slot": "0"
            }
          ],
          "erc7201:openzeppelin.storage.Initializable": [
            {
              "contract": "Initializable",
              "label": "_initialized",
              "type": "t_uint64",
              "src": "@openzeppelin/contracts-upgradeable/proxy/utils/Initializable.sol:69",
              "offset": 0,
              "slot": "0"
            },
            {
              "contract": "Initializable",
              "label": "_initializing",
              "type": "t_bool",
              "src": "@openzeppelin/contracts-upgradeable/proxy/utils/Initializable.sol:73",
              "offset": 8,
              "slot": "0"
            }
          ]
        }
      }
    }
  }
}
